uem_reader_py-0.1.2.dist-info/METADATA
uem_reader_py-0.1.2.dist-info/WHEEL
uem_reader_py/__pycache__/__init__.cpython-310.pyc
uem_reader_py/__init__.py
uem_reader_py/uem_reader_py.cpython-37m-x86_64-linux-gnu.so
uem_reader_py-0.1.2.dist-info/RECORD
